easylogging2/__init__.py
easylogging2-2.0.5.dist-info/METADATA
easylogging2-2.0.5.dist-info/RECORD
easylogging2-2.0.5.dist-info/WHEEL
easylogging2-2.0.5.dist-info/top_level.txt
