Metadata-Version: 2.1
Name: easylogging2
Version: 2.0.5
Summary: Simple Python logging lib
Home-page: https://github.com/AI35/easylogging2
Author: ALI B OTHMAN
Author-email: alosh.othman55@gmail.com
License: GNU v3.0
Project-URL: Bug Reports, https://github.com/AI35/easylogging2/issues
Project-URL: Source, https://github.com/AI35/easylogging2
Keywords: logging logger log python
Platform: UNKNOWN
Requires-Python: >=3
Requires-Dist: configparser (>=3.5.0)
